sinapsis_huggingface_grounding_dino/__init__.py
sinapsis_huggingface_grounding_dino/helpers/__init__.py
sinapsis_huggingface_grounding_dino/helpers/grounding_dino_keys.py
sinapsis_huggingface_grounding_dino/helpers/tags.py
sinapsis_huggingface_grounding_dino/templates/__init__.py
sinapsis_huggingface_grounding_dino/templates/grounding_dino.py
sinapsis_huggingface_grounding_dino/templates/grounding_dino_classification.py
sinapsis_huggingface_grounding_dino-0.1.10.dist-info/licenses/LICENSE
sinapsis_huggingface_grounding_dino-0.1.10.dist-info/METADATA
sinapsis_huggingface_grounding_dino-0.1.10.dist-info/WHEEL
sinapsis_huggingface_grounding_dino-0.1.10.dist-info/top_level.txt
sinapsis_huggingface_grounding_dino-0.1.10.dist-info/RECORD
