Metadata-Version: 2.4
Name: sinapsis-huggingface-grounding-dino
Version: 0.1.10
Summary: Templates for GroundingDINO with HuggingFace
Author-email: SinapsisAI <dev@sinapsis.tech>
Project-URL: Homepage, https://sinapsis.tech
Project-URL: Documentation, https://docs.sinapsis.tech/docs
Project-URL: Tutorials, https://docs.sinapsis.tech/tutorials
Project-URL: Repository, https://github.com/Sinapsis-AI/sinapsis-huggingface.git
Requires-Python: >=3.10
License-File: LICENSE
Requires-Dist: accelerate>=1.1.1
Requires-Dist: scipy>=1.14.1
Requires-Dist: sinapsis>=0.1.1
Requires-Dist: torch>=2.5.1
Requires-Dist: transformers>=4.47.1
Dynamic: license-file
